<?xml version='1.0' encoding='UTF-8'?>
<letter id="27337" year="1557" lang="lat">
<correspondents>
	<originator>Bullinger</originator>
	<addressee>Johannes Fabricius</addressee>
</correspondents>
<space_time>
	<place></place>
	<date>[Zwischen 1557 und 1566 vielleicht [nach Simler auf Grund der Signaturen] zu: 12. Januar 1565]</date>
</space_time>
<record>Zürich StA, E II 373, 549. /Orig.(Aut.)</record>
<print>Gr. II, 557 R.</print>
<statue></statue>
<content>
Cum intellexi a d.
Rodolpho, affine tuo, virum hic esse, cui literae tuto possint credi, inclusi has, quas vides, quas alioqui non cuivis credidissem.
Tu cura, ut mature et tuto remittantur ad me.
Vale iterum.
Praestantissimo viro d.
Ioanni Fabritio, Curiensis ecclesiae ministro fidelissimo, domino et fratri colendo et dilectissimo.
^$Chur.
</content>
</letter>