<?xml version='1.0' encoding='UTF-8'?>
<letter id="37092" year="1567" lang="lat">
<correspondents>
	<originator>Scipio [=Scipione] Lentulo [=Lentulus]</originator>
	<addressee>Bullinger</addressee>
</correspondents>
<space_time>
	<place>Chiavenna</place>
	<date>8. September 1567</date>
</space_time>
<record>Zürich StA, E II 365, 326f.</record>
<print>Gr. III, S. 29. [R].</print>
<statue></statue>
<content>
Er schickt Bullinger durch Pontisella zwei ihm, als er durch
Zürich kam ("istac praetereunti") geliehene Kronen mit Dank
zurück und bezeugt seine Verehrung.
"Quod autem ad res meas attinet, sic habeto: me discessisse
e monte Sondrii bona illius ecclesiae venia, quod labori
ferendo non essem ob meam imbecillam valetudinem (laboro
enim iandiu articulari morbo), quum vici distarent inter se
haud parum ac propterea in ea ecclesia ministerii exercitia
potius eundo vel potius itando essent conficienda quam
praedicando, quo factum, ut vocatus ab ista ecclesia, nempe
Clavennensi, huc me contulerim. Habeo hic collegam d.
Simonem Florillum, civem meum, qui te etiam atque etiam
salutat tibique humiliter se commendat."
<timestamp>Clavenna, 8. septembris 1567</timestamp>
<ps>"Est isthic quidam frater Italus Iulius
Santerentianus, olim d. Petri Martyris felicissimae memoriae
assecla. Cuperem abs te fieri certiorem(!), an eius vita et
doctrina eiusmodi sint, ut vocatus ad ministerium verbi
valeat tantam provintiam aliqua saltem cum laude sustinere
ac gerere."
</ps>
</content>
</letter>